spa_dat/__init__.py
spa_dat/application/__init__.py
spa_dat/application/application.py
spa_dat/application/typedef.py
spa_dat/config.py
spa_dat/main.py
spa_dat/provider.py
spa_dat/serialization.py
spa_dat/socket/__init__.py
spa_dat/socket/kafka.py
spa_dat/socket/mqtt.py
spa_dat/socket/typedef.py
spa_dat-0.4.0.dist-info/LICENSE
spa_dat-0.4.0.dist-info/METADATA
spa_dat-0.4.0.dist-info/WHEEL
spa_dat-0.4.0.dist-info/RECORD
